guide_seq-2.0.0.data/scripts/alignReads.py
guide_seq-2.0.0.data/scripts/filterBackgroundSites.py
guide_seq-2.0.0.data/scripts/guideseq.py
guide_seq-2.0.0.data/scripts/identifyOfftargetSites.py
guide_seq-2.0.0.data/scripts/log.py
guide_seq-2.0.0.data/scripts/validation.py
guide_seq-2.0.0.data/scripts/visualization.py
guideseq/__init__.py
guideseq/alignReads.py
guideseq/demultiplex.py
guideseq/filterBackgroundSites.py
guideseq/guideseq.py
guideseq/guideseq2.py
guideseq/guideseq_CASTmodification.py
guideseq/guideseq_dev.py
guideseq/guideseq_visualize_only.py
guideseq/identifyOfftargetSites.py
guideseq/identify_test.py
guideseq/log.py
guideseq/old_guideseq_with_demultiplexing.py
guideseq/refseq_gene_name.py
guideseq/validation.py
guideseq/visualization.py
guideseq/visualization2.py
guideseq/visualization_GV.py
guideseq/visualization_bk.py
umi/__init__.py
umi/consolidate.py
umi/demultiplex.py
umi/umitag.py
guide_seq-2.0.0.dist-info/AUTHORS.rst
guide_seq-2.0.0.dist-info/LICENSE
guide_seq-2.0.0.dist-info/METADATA
guide_seq-2.0.0.dist-info/WHEEL
guide_seq-2.0.0.dist-info/top_level.txt
guide_seq-2.0.0.dist-info/RECORD
