Metadata-Version: 2.1
Name: guide-seq
Version: 2.0.0
Summary: GUIDE-seq pipeline for GUIDE-seq and GUIDE-seq-2
Home-page: https://github.com/tsailabSJ/guideseq
Author: Yichao Li, Shengdar Q Tsai
Author-email: Yichao.Li@stjude.org
License: AGPL
Keywords: guideseq
Platform: UNKNOWN
Classifier: Development Status :: 5 - Production/Stable
Classifier: Intended Audience :: Science/Research
Classifier: Topic :: Scientific/Engineering :: Bio-Informatics
Classifier: Topic :: Scientific/Engineering :: Visualization
Classifier: Topic :: Scientific/Engineering :: Information Analysis
Classifier: License :: OSI Approved :: GNU General Public License v2 (GPLv2)
Classifier: Operating System :: Unix
Classifier: Natural Language :: English
Classifier: Programming Language :: Python :: 3
License-File: LICENSE
License-File: AUTHORS.rst
